MANIFEST.in
README.md
README.rst
setup.cfg
setup.py
leboard/VERSION
leboard/__init__.py
leboard/cli/__init__.py
leboard/storage/__init__.py
tests/leboard/test_leboard.py
tests/leboard/__pycache__/test_leboard.cpython-36-PYTEST.pyc