Metadata-Version: 1.1
Name: leboard
Version: 0.1.1
Summary: Le Board, a simple leaderboard generator for ranking your algorithms experiments
Home-page: https://github.com/GSchutz/leboard
Author: GSchutz
Author-email: guilherme@gschutz.com
License: UNKNOWN
Download-URL: https://github.com/GSchutz/leboard/archive/0.1.1.tar.gz
Keywords: leaderboard,ranking,models
Platform: UNKNOWN
